workspacex/__init__.py
workspacex/artifact.py
workspacex/artifacts/arxiv.py
workspacex/artifacts/base_pdf_processor.py
workspacex/artifacts/factory.py
workspacex/artifacts/form_definitions.py
workspacex/artifacts/langextract.py
workspacex/artifacts/novel_artifact.py
workspacex/artifacts/pdf_artifact.py
workspacex/artifacts/playwright.py
workspacex/artifacts/web_pages.py
workspacex/base.py
workspacex/chunk/base.py
workspacex/chunk/character.py
workspacex/chunk/markdown.py
workspacex/chunk/sentence.py
workspacex/chunk/smart.py
workspacex/code_artifact.py
workspacex/config.py
workspacex/embedding/base.py
workspacex/embedding/ollama.py
workspacex/embedding/openai_compatible.py
workspacex/extractor/__init__.py
workspacex/extractor/base.py
workspacex/extractor/langextractor.py
workspacex/extractor/noval_extractor.py
workspacex/fulltext/__init__.py
workspacex/fulltext/dbs/__init__.py
workspacex/fulltext/dbs/base.py
workspacex/fulltext/dbs/elasticsearch.py
workspacex/fulltext/factory.py
workspacex/handler/summary.py
workspacex/observer.py
workspacex/reranker/base.py
workspacex/reranker/bm25.py
workspacex/reranker/dashscope.py
workspacex/reranker/factory.py
workspacex/reranker/http.py
workspacex/reranker/local.py
workspacex/reranker/server/reranker_server.py
workspacex/storage/__init__.py
workspacex/storage/base.py
workspacex/storage/local.py
workspacex/storage/s3.py
workspacex/utils/common.py
workspacex/utils/io.py
workspacex/utils/logger.py
workspacex/utils/pdf.py
workspacex/utils/progress.py
workspacex/utils/rag_utils.py
workspacex/utils/scheduler.py
workspacex/utils/timeit.py
workspacex/utils/tokenutils.py
workspacex/vector/dbs/base.py
workspacex/vector/dbs/chroma.py
workspacex/vector/factory.py
workspacex/workspace.py
workspacex_mcp/__init__.py
workspacex_mcp/rag_local_cli.py
workspacex_mcp/rag_remote_cli.py
workspacex-0.1.43.dist-info/METADATA
workspacex-0.1.43.dist-info/WHEEL
workspacex-0.1.43.dist-info/RECORD
