Metadata-Version: 2.3
Name: workspacex
Version: 0.1.43
Summary: workspacex is a Python library for managing AIGC (AI-Generated Content) artifacts. It provides a collaborative workspace environment for handling multiple artifacts with features like version control, update notifications, artifact management, and pluggable storage and embedding backends.
Author: wuhulala
Author-email: xueaohui@gmail.com
Requires-Python: >=3.10,<=3.13
Classifier: Programming Language :: Python :: 3
Classifier: Programming Language :: Python :: 3.10
Classifier: Programming Language :: Python :: 3.11
Classifier: Programming Language :: Python :: 3.12
Classifier: Programming Language :: Python :: 3.13
Provides-Extra: all
Provides-Extra: chunker-sentence
Provides-Extra: mcp
Provides-Extra: reranker
Provides-Extra: reranker-server
Requires-Dist: PyPDF2 (>=3.0.1,<3.1.0)
Requires-Dist: aiohttp (>=3.12.13,<4.0.0)
Requires-Dist: chromadb (>=1.0.13,<2.0.0)
Requires-Dist: dashscope (>=1.23.4,<2.0.0)
Requires-Dist: elasticsearch (==8.17.2) ; extra == "all"
Requires-Dist: fastapi (>=0.110.0) ; extra == "all"
Requires-Dist: fastapi (>=0.110.0) ; extra == "reranker-server"
Requires-Dist: fastmcp (>=2.10.6) ; extra == "all"
Requires-Dist: fastmcp (>=2.10.6) ; extra == "mcp"
Requires-Dist: langchain (>=0.3.26,<0.4.0)
Requires-Dist: langchain-text-splitters (>=0.3.8,<0.4.0)
Requires-Dist: langchain_core (>=0.3.66,<0.4.0)
Requires-Dist: langextract (>=1.0.8,<2.0.0)
Requires-Dist: langfuse (>=3.1.3,<4.0.0)
Requires-Dist: mistune (>=3.1.3,<4.0.0)
Requires-Dist: numpy (>=1.26.4,<2.0)
Requires-Dist: openai (>=1.86.0,<2.0.0)
Requires-Dist: pydantic (>=2.11.5,<3.0.0)
Requires-Dist: python-dotenv (>=1.1.0,<2.0.0)
Requires-Dist: requests (>=2.32.4,<3.0.0)
Requires-Dist: s3fs (>=2025.5.1,<2026.0.0)
Requires-Dist: sentence_transformers (>=5.0.0) ; extra == "all"
Requires-Dist: sentence_transformers (>=5.0.0) ; extra == "chunker-sentence"
Requires-Dist: torch (==2.2.0) ; extra == "reranker-server"
Requires-Dist: torch (>=2.2.0) ; extra == "all"
Requires-Dist: torch (>=2.2.0) ; extra == "reranker"
Requires-Dist: transformers (==4.51.0) ; extra == "reranker-server"
Requires-Dist: transformers (>=4.51.0) ; extra == "all"
Requires-Dist: transformers (>=4.51.0) ; extra == "reranker"
Requires-Dist: uvicorn (>=0.27.1) ; extra == "all"
Requires-Dist: uvicorn (>=0.27.1) ; extra == "reranker-server"
